.gitignore
MANIFEST.in
README.txt
bootstrap.py
buildout.cfg
setup.py
docs/CHANGES.txt
docs/CONTRIBUTORS.txt
docs/INSTALL.txt
docs/LICENSE.GPL
docs/LICENSE.txt
src/pas/__init__.py
src/pas.plugins.memberapproval.egg-info/PKG-INFO
src/pas.plugins.memberapproval.egg-info/SOURCES.txt
src/pas.plugins.memberapproval.egg-info/dependency_links.txt
src/pas.plugins.memberapproval.egg-info/entry_points.txt
src/pas.plugins.memberapproval.egg-info/namespace_packages.txt
src/pas.plugins.memberapproval.egg-info/not-zip-safe
src/pas.plugins.memberapproval.egg-info/requires.txt
src/pas.plugins.memberapproval.egg-info/top_level.txt
src/pas/plugins/__init__.py
src/pas/plugins/memberapproval/README.txt
src/pas/plugins/memberapproval/__init__.py
src/pas/plugins/memberapproval/configure.zcml
src/pas/plugins/memberapproval/events.py
src/pas/plugins/memberapproval/install.py
src/pas/plugins/memberapproval/interfaces.py
src/pas/plugins/memberapproval/paspatch.py
src/pas/plugins/memberapproval/plugin.py
src/pas/plugins/memberapproval/setuphandlers.py
src/pas/plugins/memberapproval/utils.py
src/pas/plugins/memberapproval/browser/__init__.py
src/pas/plugins/memberapproval/browser/__init__.pyo
src/pas/plugins/memberapproval/browser/add_plugin.zpt
src/pas/plugins/memberapproval/browser/configure.zcml
src/pas/plugins/memberapproval/browser/icon.gif
src/pas/plugins/memberapproval/profiles/default/metadata.xml
src/pas/plugins/memberapproval/profiles/default/pas.plugins.memberapproval.txt
src/pas/plugins/memberapproval/tests/__init__.py
src/pas/plugins/memberapproval/tests/layer.py
src/pas/plugins/memberapproval/tests/test_plugin.py