Metadata-Version: 1.1
Name: pas.plugins.memberapproval
Version: 1.0
Summary: Member approval PAS plugin
Home-page: http://svn.plone.org/svn/collective/
Author: Radim Novotny
Author-email: novotny.radim@gmail.com
License: GPL
Keywords: plone pas
Platform: UNKNOWN
Classifier: Framework :: Plone
Classifier: Framework :: Plone :: 4.1
Classifier: Framework :: Plone :: 4.2
Classifier: Framework :: Plone :: 4.3
Classifier: Programming Language :: Python
Classifier: Programming Language :: Python :: 2.7
Classifier: Intended Audience :: Developers
Classifier: License :: OSI Approved :: GNU General Public License (GPL)
